urldb/Urldb.py
urldb/Urldblite.py
urldb/__init__.py
urlDB-0.5b1.dist-info/LICENSE
urlDB-0.5b1.dist-info/METADATA
urlDB-0.5b1.dist-info/WHEEL
urlDB-0.5b1.dist-info/top_level.txt
urlDB-0.5b1.dist-info/RECORD
