Metadata-Version: 2.1
Name: urlDB
Version: 0.5b1
Summary: Tool for nice work with storing data in URL
Home-page: https://github.com/WhiteApfel/urlDB
Author: WhiteApfel
Author-email: white@pfel.ru
License: Mozilla Public License 2.0
Platform: UNKNOWN
Requires-Dist: ujson
Requires-Dist: pyperclip
Requires-Dist: setuptools
